continue_tts/__init__.py
continue_tts/decoder.py
continue_tts/engine_class.py
continue_speech-1.0.2.dist-info/METADATA
continue_speech-1.0.2.dist-info/WHEEL
continue_speech-1.0.2.dist-info/top_level.txt
continue_speech-1.0.2.dist-info/RECORD
