Metadata-Version: 2.4
Name: continue-speech
Version: 1.0.2
Summary: Continue-TTS Text-to-Speech System
Home-page: https://github.com/SVECTOR-CORPORATION/Continue-TTS
Author: SVECTOR
Author-email: team@svector.co.in
Classifier: Programming Language :: Python :: 3
Classifier: License :: OSI Approved :: Apache Software License
Classifier: Operating System :: OS Independent
Requires-Python: >=3.8
Requires-Dist: snac
Requires-Dist: vllm
Dynamic: author
Dynamic: author-email
Dynamic: classifier
Dynamic: description
Dynamic: description-content-type
Dynamic: home-page
Dynamic: requires-dist
Dynamic: requires-python
Dynamic: summary
